[
    {
        "index": 1,
        "heading": "Usage",
        "html": "<nav class=\"uk-navbar-container\" uk-navbar>\n    <div class=\"uk-navbar-left\">\n\n        <ul class=\"uk-navbar-nav\">\n            <li class=\"uk-active\"><a href=\"#\">Active</a></li>\n            <li>\n                <a href=\"#\">Parent</a>\n                <div class=\"uk-navbar-dropdown\">\n                    <ul class=\"uk-nav uk-navbar-dropdown-nav\">\n                        <li class=\"uk-active\"><a href=\"#\">Active</a></li>\n                        <li><a href=\"#\">Item</a></li>\n                        <li><a href=\"#\">Item</a></li>\n                    </ul>\n                </div>\n            </li>\n            <li><a href=\"#\">Item</a></li>\n        </ul>\n\n    </div>\n</nav>"
    },
    {
        "index": 2,
        "heading": "",
        "html": "<nav class=\"uk-navbar-container\">\n    <div class=\"uk-container\">\n        <div uk-navbar>\n\n            <div class=\"uk-navbar-left\">\n\n                <ul class=\"uk-navbar-nav\">\n                    <li class=\"uk-active\"><a href=\"#\">Active</a></li>\n                    <li>\n                        <a href=\"#\">Parent</a>\n                        <div class=\"uk-navbar-dropdown\">\n                            <ul class=\"uk-nav uk-navbar-dropdown-nav\">\n                                <li class=\"uk-active\"><a href=\"#\">Active</a></li>\n                                <li><a href=\"#\">Item</a></li>\n                                <li><a href=\"#\">Item</a></li>\n                            </ul>\n                        </div>\n                    </li>\n                    <li><a href=\"#\">Item</a></li>\n                </ul>\n\n            </div>\n\n        </div>\n    </div>\n</nav>"
    },
    {
        "index": 3,
        "heading": "Multiple navigations",
        "html": "<nav class=\"uk-navbar-container\">\n    <div class=\"uk-container\">\n        <div uk-navbar>\n\n            <div class=\"uk-navbar-left\">\n\n                <ul class=\"uk-navbar-nav\">\n                    <li class=\"uk-active\"><a href=\"#\">Active</a></li>\n                    <li>\n                        <a href=\"#\">Parent</a>\n                        <div class=\"uk-navbar-dropdown\">\n                            <ul class=\"uk-nav uk-navbar-dropdown-nav\">\n                                <li class=\"uk-active\"><a href=\"#\">Active</a></li>\n                                <li><a href=\"#\">Item</a></li>\n                                <li><a href=\"#\">Item</a></li>\n                            </ul>\n                        </div>\n                    </li>\n                    <li><a href=\"#\">Item</a></li>\n                </ul>\n\n            </div>\n\n            <div class=\"uk-navbar-right\">\n\n                <ul class=\"uk-navbar-nav\">\n                    <li class=\"uk-active\"><a href=\"#\">Active</a></li>\n                    <li>\n                        <a href=\"#\">Parent</a>\n                        <div class=\"uk-navbar-dropdown\">\n                            <ul class=\"uk-nav uk-navbar-dropdown-nav\">\n                                <li class=\"uk-active\"><a href=\"#\">Active</a></li>\n                                <li><a href=\"#\">Item</a></li>\n                                <li><a href=\"#\">Item</a></li>\n                            </ul>\n                        </div>\n                    </li>\n                    <li><a href=\"#\">Item</a></li>\n                </ul>\n\n            </div>\n\n        </div>\n    </div>\n</nav>"
    },
    {
        "index": 4,
        "heading": "Transparent modifier",
        "html": "<div class=\"uk-position-relative\">\n    <img src=\"images/light.jpg\" width=\"1800\" height=\"1200\" alt=\"\">\n    <div class=\"uk-position-top\">\n        <nav class=\"uk-navbar-container uk-navbar-transparent\">\n            <div class=\"uk-container\">\n                <div uk-navbar>\n\n                    <div class=\"uk-navbar-left\">\n                        <ul class=\"uk-navbar-nav\">\n                            <li class=\"uk-active\"><a href=\"#\">Active</a></li>\n                            <li><a href=\"#\">Item</a></li>\n                            <li>\n                                <a href=\"#\">Parent</a>\n                                <div class=\"uk-navbar-dropdown\">\n                                    <ul class=\"uk-nav uk-navbar-dropdown-nav\">\n                                        <li class=\"uk-active\"><a href=\"#\">Active</a></li>\n                                        <li><a href=\"#\">Item</a></li>\n                                        <li class=\"uk-nav-header\">Header</li>\n                                        <li><a href=\"#\">Item</a></li>\n                                        <li><a href=\"#\">Item</a></li>\n                                        <li class=\"uk-nav-divider\"></li>\n                                        <li><a href=\"#\">Item</a></li>\n                                    </ul>\n                                </div>\n                            </li>\n                        </ul>\n                    </div>\n\n                </div>\n            </div>\n        </nav>\n    </div>\n</div>"
    },
    {
        "index": 5,
        "heading": "Subtitle",
        "html": "<nav class=\"uk-navbar-container\">\n    <div class=\"uk-container\">\n        <div uk-navbar>\n                \n            <div class=\"uk-navbar-left\">\n\n                <ul class=\"uk-navbar-nav\">\n                    <li class=\"uk-active\">\n                        <a href=\"#\">\n                            <div>\n                                Active\n                                <div class=\"uk-navbar-subtitle\">Subtitle</div>\n                            </div>\n                        </a>\n                    </li>\n                    <li>\n                        <a href=\"#\">\n                            <div>\n                                Parent\n                                <div class=\"uk-navbar-subtitle\">Subtitle</div>\n                            </div>\n                        </a>\n                        <div class=\"uk-navbar-dropdown\">\n                            <ul class=\"uk-nav uk-navbar-dropdown-nav\">\n                                <li class=\"uk-active\"><a href=\"#\">Active</a></li>\n                                <li><a href=\"#\">Item</a></li>\n                                <li><a href=\"#\">Item</a></li>\n                            </ul>\n                        </div>\n                    </li>\n                    <li>\n                        <a href=\"#\">\n                            <div>\n                                Item\n                                <div class=\"uk-navbar-subtitle\">Subtitle</div>\n                            </div>\n                        </a>\n                    </li>\n                </ul>\n\n            </div>\n\n        </div>\n    </div>\n</nav>"
    },
    {
        "index": 6,
        "heading": "Content item",
        "html": "<nav class=\"uk-navbar-container\">\n    <div class=\"uk-container\">\n        <div uk-navbar>\n\n            <div class=\"uk-navbar-left\">\n\n                <a class=\"uk-navbar-item uk-logo\" href=\"#\" aria-label=\"Back to Home\">Logo</a>\n\n                <ul class=\"uk-navbar-nav\">\n                    <li>\n                        <a href=\"#\">\n                            <span class=\"uk-icon uk-margin-xsmall-right\" uk-icon=\"icon: star\"></span>\n                            Features\n                        </a>\n                    </li>\n                </ul>\n\n                <div class=\"uk-navbar-item\">\n                    <div>Some <a href=\"#\">Link</a></div>\n                </div>\n\n                <div class=\"uk-navbar-item\">\n                    <form action=\"javascript:void(0)\">\n                        <input class=\"uk-input uk-form-width-small\" type=\"text\" placeholder=\"Input\" aria-label=\"Input\">\n                        <button class=\"uk-button uk-button-default\">Button</button>\n                    </form>\n                </div>\n\n            </div>\n\n        </div>\n    </div>\n</nav>"
    },
    {
        "index": 7,
        "heading": "Centered logo",
        "html": "<nav class=\"uk-navbar-container\">\n    <div class=\"uk-container\">\n        <div uk-navbar>\n\n            <div class=\"uk-navbar-center\">\n\n                <div class=\"uk-navbar-center-left\">\n                    <ul class=\"uk-navbar-nav\">\n                        <li class=\"uk-active\"><a href=\"#\">Active</a></li>\n                        <li>\n                            <a href=\"#\">Parent</a>\n                            <div class=\"uk-navbar-dropdown\">\n                                <ul class=\"uk-nav uk-navbar-dropdown-nav\">\n                                    <li class=\"uk-active\"><a href=\"#\">Active</a></li>\n                                    <li><a href=\"#\">Item</a></li>\n                                    <li><a href=\"#\">Item</a></li>\n                                </ul>\n                            </div>\n                        </li>\n                    </ul>\n                </div>\n                <a class=\"uk-navbar-item uk-logo\" href=\"#\">Logo</a>\n                <div class=\"uk-navbar-center-right\">\n                    <ul class=\"uk-navbar-nav\">\n                        <li><a href=\"#\">Item</a></li>\n                        <li><a href=\"#\">Item</a></li>\n                    </ul>\n                </div>\n\n            </div>\n\n        </div>\n    </div>\n</nav>"
    },
    {
        "index": 8,
        "heading": "Toggle item",
        "html": "<nav class=\"uk-navbar-container uk-margin\">\n    <div class=\"uk-container\">\n        <div uk-navbar=\"mode: click\">\n\n            <div class=\"uk-navbar-left\">\n                <a class=\"uk-navbar-toggle\" uk-navbar-toggle-icon href=\"#\"></a>\n                <div class=\"uk-navbar-dropdown\">\n                    <ul class=\"uk-nav uk-navbar-dropdown-nav\">\n                        <li class=\"uk-active\"><a href=\"#\">Active</a></li>\n                        <li><a href=\"#\">Item</a></li>\n                        <li><a href=\"#\">Item</a></li>\n                    </ul>\n                </div>\n            </div>\n        \n        </div>\n    </div>\n</nav>\n\n<nav class=\"uk-navbar-container uk-margin\">\n    <div class=\"uk-container\">\n        <div uk-navbar=\"mode: click\">\n\n            <div class=\"uk-navbar-left\">\n                <a class=\"uk-navbar-toggle\" href=\"#\">\n                    <span uk-navbar-toggle-icon></span> <span class=\"uk-margin-xsmall-left\">Menu</span>\n                </a>\n                <div class=\"uk-navbar-dropdown\">\n                    <ul class=\"uk-nav uk-navbar-dropdown-nav\">\n                        <li class=\"uk-active\"><a href=\"#\">Active</a></li>\n                        <li><a href=\"#\">Item</a></li>\n                        <li><a href=\"#\">Item</a></li>\n                    </ul>\n                </div>\n            </div>\n\n        </div>\n    </div>\n</nav>"
    },
    {
        "index": 9,
        "heading": "Dropdowns",
        "html": "<nav class=\"uk-navbar-container\">\n    <div class=\"uk-container\">\n        <div uk-navbar>\n\n            <div class=\"uk-navbar-left\">\n\n                <ul class=\"uk-navbar-nav\">\n                    <li class=\"uk-active\"><a href=\"#\">Active</a></li>\n                    <li>\n                        <a href=\"#\">Parent</a>\n                        <div class=\"uk-navbar-dropdown\">\n                            <ul class=\"uk-nav uk-navbar-dropdown-nav\">\n                                <li class=\"uk-active\"><a href=\"#\">Active</a></li>\n                                <li><a href=\"#\">Item</a></li>\n                                <li class=\"uk-nav-header\">Header</li>\n                                <li><a href=\"#\">Item</a></li>\n                                <li><a href=\"#\">Item</a></li>\n                                <li class=\"uk-nav-divider\"></li>\n                                <li><a href=\"#\">Item</a></li>\n                            </ul>\n                        </div>\n                    </li>\n                    <li><a href=\"#\">Item</a></li>\n                </ul>\n\n            </div>\n            <div class=\"uk-navbar-right\">\n\n                <ul class=\"uk-navbar-nav\">\n                    <li>\n                        <a href=\"#\">Parent</a>\n                        <div class=\"uk-navbar-dropdown\">\n                            <ul class=\"uk-nav uk-navbar-dropdown-nav\">\n                                <li class=\"uk-active\"><a href=\"#\">Active</a></li>\n                                <li><a href=\"#\">Item</a></li>\n                                <li class=\"uk-nav-header\">Header</li>\n                                <li><a href=\"#\">Item</a></li>\n                                <li><a href=\"#\">Item</a></li>\n                                <li class=\"uk-nav-divider\"></li>\n                                <li><a href=\"#\">Item</a></li>\n                            </ul>\n                        </div>\n                    </li>\n                </ul>\n            </div>\n\n        </div>\n    </div>\n</nav>"
    },
    {
        "index": 10,
        "heading": "Click mode",
        "html": "<nav class=\"uk-navbar-container\">\n    <div class=\"uk-container\">\n        <div uk-navbar=\"mode: click\">\n\n            <div class=\"uk-navbar-left\">\n\n                <ul class=\"uk-navbar-nav\">\n                    <li class=\"uk-active\"><a href=\"#\">Active</a></li>\n                    <li>\n                        <a href=\"#\">Parent</a>\n                        <div class=\"uk-navbar-dropdown\">\n                            <ul class=\"uk-nav uk-navbar-dropdown-nav\">\n                                <li class=\"uk-active\"><a href=\"#\">Active</a></li>\n                                <li><a href=\"#\">Item</a></li>\n                                <li><a href=\"#\">Item</a></li>\n                            </ul>\n                        </div>\n                    </li>\n                    <li><a href=\"#\">Item</a></li>\n                </ul>\n\n            </div>\n\n        </div>\n    </div>\n</nav>"
    },
    {
        "index": 11,
        "heading": "Alignment",
        "html": "<nav class=\"uk-navbar-container\">\n    <div class=\"uk-container\">\n        <div uk-navbar=\"align: center\">\n\n            <div class=\"uk-navbar-center\">\n\n                <ul class=\"uk-navbar-nav\">\n                    <li>\n                        <a href=\"#\">Parent</a>\n                        <div class=\"uk-navbar-dropdown\">\n                            <ul class=\"uk-nav uk-navbar-dropdown-nav\">\n                                <li class=\"uk-active\"><a href=\"#\">Active</a></li>\n                                <li><a href=\"#\">Item</a></li>\n                                <li><a href=\"#\">Item</a></li>\n                            </ul>\n                        </div>\n                    </li>\n                </ul>\n\n            </div>\n\n        </div>\n    </div>\n</nav>"
    },
    {
        "index": 12,
        "heading": "Target",
        "html": "<nav class=\"uk-navbar-container\">\n    <div class=\"uk-container\">\n        <div uk-navbar=\"target: !.uk-navbar; align: center\">\n\n            <div class=\"uk-navbar-left\">\n\n                <ul class=\"uk-navbar-nav\">\n                    <li>\n                        <a href=\"#\">Parent</a>\n                        <div class=\"uk-navbar-dropdown\">\n                            <ul class=\"uk-nav uk-navbar-dropdown-nav\">\n                                <li class=\"uk-active\"><a href=\"#\">Active</a></li>\n                                <li><a href=\"#\">Item</a></li>\n                                <li class=\"uk-nav-header\">Header</li>\n                                <li><a href=\"#\">Item</a></li>\n                                <li><a href=\"#\">Item</a></li>\n                                <li class=\"uk-nav-divider\"></li>\n                                <li><a href=\"#\">Item</a></li>\n                            </ul>\n                        </div>\n                    </li>\n                    <li>\n                        <a href=\"#\">Parent</a>\n                        <div class=\"uk-navbar-dropdown uk-navbar-dropdown-width-2\">\n                            <div class=\"uk-drop-grid uk-child-width-1-2\" uk-grid>\n                                <div>\n                                    <ul class=\"uk-nav uk-navbar-dropdown-nav\">\n                                        <li class=\"uk-active\"><a href=\"#\">Active</a></li>\n                                        <li><a href=\"#\">Item</a></li>\n                                        <li class=\"uk-nav-header\">Header</li>\n                                        <li><a href=\"#\">Item</a></li>\n                                        <li><a href=\"#\">Item</a></li>\n                                        <li class=\"uk-nav-divider\"></li>\n                                        <li><a href=\"#\">Item</a></li>\n                                    </ul>\n                                </div>\n                                <div>\n                                    <ul class=\"uk-nav uk-navbar-dropdown-nav\">\n                                        <li class=\"uk-active\"><a href=\"#\">Active</a></li>\n                                        <li><a href=\"#\">Item</a></li>\n                                        <li class=\"uk-nav-header\">Header</li>\n                                        <li><a href=\"#\">Item</a></li>\n                                        <li><a href=\"#\">Item</a></li>\n                                        <li class=\"uk-nav-divider\"></li>\n                                        <li><a href=\"#\">Item</a></li>\n                                    </ul>\n                                </div>\n                            </div>\n                        </div>\n                    </li>\n                    <li>\n                        <a href=\"#\">Parent</a>\n                        <div class=\"uk-navbar-dropdown uk-navbar-dropdown-width-3\">\n                            <div class=\"uk-drop-grid uk-child-width-1-3\" uk-grid>\n                                <div>\n                                    <ul class=\"uk-nav uk-navbar-dropdown-nav\">\n                                        <li class=\"uk-active\"><a href=\"#\">Active</a></li>\n                                        <li><a href=\"#\">Item</a></li>\n                                        <li class=\"uk-nav-header\">Header</li>\n                                        <li><a href=\"#\">Item</a></li>\n                                        <li><a href=\"#\">Item</a></li>\n                                        <li class=\"uk-nav-divider\"></li>\n                                        <li><a href=\"#\">Item</a></li>\n                                    </ul>\n                                </div>\n                                <div>\n                                    <ul class=\"uk-nav uk-navbar-dropdown-nav\">\n                                        <li class=\"uk-active\"><a href=\"#\">Active</a></li>\n                                        <li><a href=\"#\">Item</a></li>\n                                        <li class=\"uk-nav-header\">Header</li>\n                                        <li><a href=\"#\">Item</a></li>\n                                        <li><a href=\"#\">Item</a></li>\n                                        <li class=\"uk-nav-divider\"></li>\n                                        <li><a href=\"#\">Item</a></li>\n                                    </ul>\n                                </div>\n                                <div>\n                                    <ul class=\"uk-nav uk-navbar-dropdown-nav\">\n                                        <li class=\"uk-active\"><a href=\"#\">Active</a></li>\n                                        <li><a href=\"#\">Item</a></li>\n                                        <li class=\"uk-nav-header\">Header</li>\n                                        <li><a href=\"#\">Item</a></li>\n                                        <li><a href=\"#\">Item</a></li>\n                                        <li class=\"uk-nav-divider\"></li>\n                                        <li><a href=\"#\">Item</a></li>\n                                    </ul>\n                                </div>\n                            </div>\n                        </div>\n                    </li>\n                </ul>\n\n            </div>\n\n            <div class=\"uk-navbar-right\">\n                <ul class=\"uk-navbar-nav\">\n                    <li>\n                        <a href=\"#\">Parent</a>\n                        <div class=\"uk-navbar-dropdown\">\n                            <ul class=\"uk-nav uk-navbar-dropdown-nav\">\n                                <li class=\"uk-active\"><a href=\"#\">Active</a></li>\n                                <li><a href=\"#\">Item</a></li>\n                                <li class=\"uk-nav-header\">Header</li>\n                                <li><a href=\"#\">Item</a></li>\n                                <li><a href=\"#\">Item</a></li>\n                                <li class=\"uk-nav-divider\"></li>\n                                <li><a href=\"#\">Item</a></li>\n                            </ul>\n                        </div>\n                    </li>\n                </ul>\n            </div>\n\n        </div>\n    </div>\n</nav>"
    },
    {
        "index": 13,
        "heading": "Dropbar",
        "html": "<div class=\"uk-position-relative\">\n\n    <nav class=\"uk-navbar-container\">\n        <div class=\"uk-container\">\n            <div uk-navbar=\"dropbar: true; dropbar-anchor: !.uk-navbar-container; target-y: !.uk-navbar-container\">\n\n                <div class=\"uk-navbar-left\">\n\n                    <ul class=\"uk-navbar-nav\">\n                        <li class=\"uk-active\"><a href=\"#\">Active</a></li>\n                        <li>\n                            <a href=\"#\">Parent</a>\n                            <div class=\"uk-navbar-dropdown\">\n                                <ul class=\"uk-nav uk-navbar-dropdown-nav\">\n                                    <li class=\"uk-active\"><a href=\"#\">Active</a></li>\n                                    <li><a href=\"#\">Item</a></li>\n                                    <li class=\"uk-nav-header\">Header</li>\n                                    <li><a href=\"#\">Item</a></li>\n                                    <li><a href=\"#\">Item</a></li>\n                                    <li class=\"uk-nav-divider\"></li>\n                                    <li><a href=\"#\">Item</a></li>\n                                </ul>\n                            </div>\n                        </li>\n                        <li>\n                            <a href=\"#\">Parent</a>\n                            <div class=\"uk-navbar-dropdown uk-navbar-dropdown-width-2\">\n                                <div class=\"uk-drop-grid uk-child-width-1-2\" uk-grid>\n                                    <div>\n                                        <ul class=\"uk-nav uk-navbar-dropdown-nav\">\n                                            <li class=\"uk-active\"><a href=\"#\">Active</a></li>\n                                            <li><a href=\"#\">Item</a></li>\n                                            <li class=\"uk-nav-header\">Header</li>\n                                            <li><a href=\"#\">Item</a></li>\n                                            <li><a href=\"#\">Item</a></li>\n                                            <li class=\"uk-nav-divider\"></li>\n                                            <li><a href=\"#\">Item</a></li>\n                                        </ul>\n                                    </div>\n                                    <div>\n                                        <ul class=\"uk-nav uk-navbar-dropdown-nav\">\n                                            <li class=\"uk-active\"><a href=\"#\">Active</a></li>\n                                            <li><a href=\"#\">Item</a></li>\n                                            <li class=\"uk-nav-header\">Header</li>\n                                            <li><a href=\"#\">Item</a></li>\n                                            <li><a href=\"#\">Item</a></li>\n                                            <li class=\"uk-nav-divider\"></li>\n                                            <li><a href=\"#\">Item</a></li>\n                                        </ul>\n                                    </div>\n                                </div>\n                            </div>\n                        </li>\n                    </ul>\n\n                </div>\n\n                <div class=\"uk-navbar-right\">\n\n                    <ul class=\"uk-navbar-nav\">\n                        <li>\n                            <a href=\"#\">Parent</a>\n                            <div class=\"uk-navbar-dropdown\">\n                                <ul class=\"uk-nav uk-navbar-dropdown-nav\">\n                                    <li class=\"uk-active\"><a href=\"#\">Active</a></li>\n                                    <li><a href=\"#\">Item</a></li>\n                                    <li class=\"uk-nav-header\">Header</li>\n                                    <li><a href=\"#\">Item</a></li>\n                                    <li><a href=\"#\">Item</a></li>\n                                    <li class=\"uk-nav-divider\"></li>\n                                    <li><a href=\"#\">Item</a></li>\n                                </ul>\n                            </div>\n                        </li>\n                    </ul>\n\n                </div>\n\n            </div>\n        </div>\n    </nav>\n\n</div>"
    },
    {
        "index": 14,
        "heading": "Stretch",
        "html": "<nav class=\"uk-navbar-container\">\n    <div class=\"uk-container\">\n        <div uk-navbar>\n\n            <div class=\"uk-navbar-left\">\n\n                <ul class=\"uk-navbar-nav\">\n                    <li class=\"uk-active\"><a href=\"#\">Active</a></li>\n                    <li>\n                        <a href>Parent</a>\n                        <div class=\"uk-navbar-dropdown\" uk-drop=\"boundary: !.uk-navbar; stretch: x; flip: false\">\n                            <ul class=\"uk-nav uk-navbar-dropdown-nav\">\n                                <li class=\"uk-active\"><a href=\"#\">Active</a></li>\n                                <li><a href=\"#\">Item</a></li>\n                                <li class=\"uk-nav-header\">Header</li>\n                                <li><a href=\"#\">Item</a></li>\n                                <li><a href=\"#\">Item</a></li>\n                                <li class=\"uk-nav-divider\"></li>\n                                <li><a href=\"#\">Item</a></li>\n                            </ul>\n                        </div>\n                    </li>\n                    <li>\n                        <a href>Parent</a>\n                        <div class=\"uk-navbar-dropdown\" uk-drop=\"boundary: !.uk-navbar; stretch: x; flip: false\">\n                            <div class=\"uk-drop-grid uk-child-width-1-2\" uk-grid>\n                                <div>\n                                    <ul class=\"uk-nav uk-navbar-dropdown-nav\">\n                                        <li class=\"uk-active\"><a href=\"#\">Active</a></li>\n                                        <li><a href=\"#\">Item</a></li>\n                                        <li class=\"uk-nav-header\">Header</li>\n                                        <li><a href=\"#\">Item</a></li>\n                                        <li><a href=\"#\">Item</a></li>\n                                        <li class=\"uk-nav-divider\"></li>\n                                        <li><a href=\"#\">Item</a></li>\n                                    </ul>\n                                </div>\n                                <div>\n                                    <ul class=\"uk-nav uk-navbar-dropdown-nav\">\n                                        <li class=\"uk-active\"><a href=\"#\">Active</a></li>\n                                        <li><a href=\"#\">Item</a></li>\n                                        <li class=\"uk-nav-header\">Header</li>\n                                        <li><a href=\"#\">Item</a></li>\n                                        <li><a href=\"#\">Item</a></li>\n                                        <li class=\"uk-nav-divider\"></li>\n                                        <li><a href=\"#\">Item</a></li>\n                                    </ul>\n                                </div>\n                            </div>\n                        </div>\n                    </li>\n                </ul>\n\n            </div>\n\n        </div>\n    </div>\n</nav>"
    },
    {
        "index": 15,
        "heading": "Parent icon",
        "html": "<nav class=\"uk-navbar-container\">\n    <div class=\"uk-container\">\n        <div uk-navbar>\n\n            <div class=\"uk-navbar-left\">\n\n                <ul class=\"uk-navbar-nav\">\n                    <li class=\"uk-active\"><a href=\"#\">Active</a></li>\n                    <li>\n                        <a href=\"#\">Parent <span uk-navbar-parent-icon></span></a>\n                        <div class=\"uk-navbar-dropdown\">\n                            <ul class=\"uk-nav uk-navbar-dropdown-nav\">\n                                <li class=\"uk-active\"><a href=\"#\">Active</a></li>\n                                <li><a href=\"#\">Item</a></li>\n                                <li class=\"uk-nav-header\">Header</li>\n                                <li><a href=\"#\">Item</a></li>\n                                <li><a href=\"#\">Item</a></li>\n                                <li class=\"uk-nav-divider\"></li>\n                                <li><a href=\"#\">Item</a></li>\n                            </ul>\n                        </div>\n                    </li>\n                    <li><a href=\"#\">Item</a></li>\n                </ul>\n\n            </div>\n            <div class=\"uk-navbar-right\">\n\n                <ul class=\"uk-navbar-nav\">\n                    <li>\n                        <a href=\"#\">Parent <span uk-navbar-parent-icon></span></a>\n                        <div class=\"uk-navbar-dropdown\">\n                            <ul class=\"uk-nav uk-navbar-dropdown-nav\">\n                                <li class=\"uk-active\"><a href=\"#\">Active</a></li>\n                                <li><a href=\"#\">Item</a></li>\n                                <li class=\"uk-nav-header\">Header</li>\n                                <li><a href=\"#\">Item</a></li>\n                                <li><a href=\"#\">Item</a></li>\n                                <li class=\"uk-nav-divider\"></li>\n                                <li><a href=\"#\">Item</a></li>\n                            </ul>\n                        </div>\n                    </li>\n                </ul>\n            </div>\n\n        </div>\n    </div>\n</nav>"
    },
    {
        "index": 16,
        "heading": "Width and Grid",
        "html": "<nav class=\"uk-navbar-container\">\n    <div class=\"uk-container\">\n        <div uk-navbar>\n\n            <div class=\"uk-navbar-left\">\n\n                <ul class=\"uk-navbar-nav\">\n                    <li>\n                        <a href=\"#\">Two Columns</a>\n                        <div class=\"uk-navbar-dropdown uk-navbar-dropdown-width-2\">\n                            <div class=\"uk-drop-grid uk-child-width-1-2\" uk-grid>\n                                <div>\n                                    <ul class=\"uk-nav uk-navbar-dropdown-nav\">\n                                        <li class=\"uk-active\"><a href=\"#\">Active</a></li>\n                                        <li><a href=\"#\">Item</a></li>\n                                        <li class=\"uk-nav-header\">Header</li>\n                                        <li><a href=\"#\">Item</a></li>\n                                        <li><a href=\"#\">Item</a></li>\n                                        <li class=\"uk-nav-divider\"></li>\n                                        <li><a href=\"#\">Item</a></li>\n                                    </ul>\n                                </div>\n                                <div>\n                                    <ul class=\"uk-nav uk-navbar-dropdown-nav\">\n                                        <li class=\"uk-active\"><a href=\"#\">Active</a></li>\n                                        <li><a href=\"#\">Item</a></li>\n                                        <li class=\"uk-nav-header\">Header</li>\n                                        <li><a href=\"#\">Item</a></li>\n                                        <li><a href=\"#\">Item</a></li>\n                                        <li class=\"uk-nav-divider\"></li>\n                                        <li><a href=\"#\">Item</a></li>\n                                    </ul>\n                                </div>\n                            </div>\n                        </div>\n                    </li>\n                </ul>\n\n            </div>\n\n        </div>\n    </div>\n</nav>"
    },
    {
        "index": 17,
        "heading": "Sticky Navbar",
        "html": "<div uk-sticky=\"sel-target: .uk-navbar-container; cls-active: uk-navbar-sticky; end: + *; offset: 80\">\n\n    <nav class=\"uk-navbar-container\">\n        <div class=\"uk-container\">\n            <div uk-navbar>\n\n                <div class=\"uk-navbar-left\">\n\n                    <ul class=\"uk-navbar-nav\">\n                        <li class=\"uk-active\"><a href=\"#\">Active</a></li>\n                        <li>\n                            <a href=\"#\">Parent</a>\n                            <div class=\"uk-navbar-dropdown\">\n                                <ul class=\"uk-nav uk-navbar-dropdown-nav\">\n                                    <li class=\"uk-active\"><a href=\"#\">Active</a></li>\n                                    <li><a href=\"#\">Item</a></li>\n                                    <li><a href=\"#\">Item</a></li>\n                                </ul>\n                            </div>\n                        </li>\n                        <li><a href=\"#\">Item</a></li>\n                    </ul>\n\n                </div>\n\n            </div>\n        </div>\n    </nav>\n\n</div>\n\n<div class=\"uk-section uk-section-secondary uk-background-cover\" style=\"background-image: url('images/dark.jpg');\">\n    <div class=\"uk-container\">\n\n        <p>Lorem ipsum dolor sit amet, consectetur adipiscing elit, sed do eiusmod tempor incididunt ut labore et dolore magna aliqua. Ut enim ad minim veniam, quis nostrud exercitation ullamco laboris nisi ut aliquip ex ea commodo consequat. Duis aute irure dolor in reprehenderit in voluptate velit esse cillum.</p>\n\n        <p>Excepteur sint occaecat cupidatat non proident, sunt in culpa qui officia deserunt mollit anim id est laborum. Lorem ipsum dolor sit amet, consectetur adipiscing elit, sed do eiusmod tempor incididunt ut labore et dolore magna aliqua. Ut enim ad minim veniam, quis nostrud exercitation ullamco laboris.</p>\n\n        <p>Lorem ipsum dolor sit amet, consectetur adipiscing elit, sed do eiusmod tempor incididunt ut labore et dolore magna aliqua. Ut enim ad minim veniam, quis nostrud exercitation ullamco laboris nisi ut aliquip ex ea commodo consequat. Duis aute irure dolor in reprehenderit in voluptate velit esse cillum.</p>\n\n    </div>\n</div>"
    },
    {
        "index": 18,
        "heading": "",
        "html": "<div uk-sticky=\"sel-target: .uk-navbar-container; cls-active: uk-navbar-sticky; end: + *; offset: 80\">\n\n    <nav class=\"uk-navbar-container\">\n        <div class=\"uk-container\">\n            <div uk-navbar=\"dropbar: true; dropbar-anchor: !.uk-navbar-container; target-y: !.uk-navbar-container\">\n\n                <div class=\"uk-navbar-left\">\n\n                    <ul class=\"uk-navbar-nav\">\n                        <li class=\"uk-active\"><a href=\"#\">Active</a></li>\n                        <li>\n                            <a href=\"#\">Parent</a>\n                            <div class=\"uk-navbar-dropdown\">\n                                <ul class=\"uk-nav uk-navbar-dropdown-nav\">\n                                    <li class=\"uk-active\"><a href=\"#\">Active</a></li>\n                                    <li><a href=\"#\">Item</a></li>\n                                    <li class=\"uk-nav-header\">Header</li>\n                                    <li><a href=\"#\">Item</a></li>\n                                    <li><a href=\"#\">Item</a></li>\n                                    <li class=\"uk-nav-divider\"></li>\n                                    <li><a href=\"#\">Item</a></li>\n                                </ul>\n                            </div>\n                        </li>\n                        <li>\n                            <a href=\"#\">Parent</a>\n                            <div class=\"uk-navbar-dropdown uk-navbar-dropdown-width-2\">\n                                <div class=\"uk-drop-grid uk-child-width-1-2\" uk-grid>\n                                    <div>\n                                        <ul class=\"uk-nav uk-navbar-dropdown-nav\">\n                                            <li class=\"uk-active\"><a href=\"#\">Active</a></li>\n                                            <li><a href=\"#\">Item</a></li>\n                                            <li class=\"uk-nav-header\">Header</li>\n                                            <li><a href=\"#\">Item</a></li>\n                                            <li><a href=\"#\">Item</a></li>\n                                            <li class=\"uk-nav-divider\"></li>\n                                            <li><a href=\"#\">Item</a></li>\n                                        </ul>\n                                    </div>\n                                    <div>\n                                        <ul class=\"uk-nav uk-navbar-dropdown-nav\">\n                                            <li class=\"uk-active\"><a href=\"#\">Active</a></li>\n                                            <li><a href=\"#\">Item</a></li>\n                                            <li class=\"uk-nav-header\">Header</li>\n                                            <li><a href=\"#\">Item</a></li>\n                                            <li><a href=\"#\">Item</a></li>\n                                            <li class=\"uk-nav-divider\"></li>\n                                            <li><a href=\"#\">Item</a></li>\n                                        </ul>\n                                    </div>\n                                </div>\n                            </div>\n                        </li>\n                    </ul>\n\n                </div>\n\n            </div>\n        </div>\n    </nav>\n\n</div>\n\n<div class=\"uk-section uk-section-secondary uk-background-cover\" style=\"background-image: url('images/dark.jpg');\">\n    <div class=\"uk-container\">\n\n        <p>Lorem ipsum dolor sit amet, consectetur adipiscing elit, sed do eiusmod tempor incididunt ut labore et dolore magna aliqua. Ut enim ad minim veniam, quis nostrud exercitation ullamco laboris nisi ut aliquip ex ea commodo consequat. Duis aute irure dolor in reprehenderit in voluptate velit esse cillum.</p>\n\n        <p>Excepteur sint occaecat cupidatat non proident, sunt in culpa qui officia deserunt mollit anim id est laborum. Lorem ipsum dolor sit amet, consectetur adipiscing elit, sed do eiusmod tempor incididunt ut labore et dolore magna aliqua. Ut enim ad minim veniam, quis nostrud exercitation ullamco laboris.</p>\n\n        <p>Lorem ipsum dolor sit amet, consectetur adipiscing elit, sed do eiusmod tempor incididunt ut labore et dolore magna aliqua. Ut enim ad minim veniam, quis nostrud exercitation ullamco laboris nisi ut aliquip ex ea commodo consequat. Duis aute irure dolor in reprehenderit in voluptate velit esse cillum.</p>\n\n    </div>\n</div>"
    },
    {
        "index": 19,
        "heading": "Transparent sticky navbar",
        "html": "<div class=\"uk-section-secondary uk-background-cover uk-preserve-color\" style=\"background-image: url('images/dark.jpg');\">\n\n    <div uk-sticky=\"start: 170; animation: uk-animation-slide-top; sel-target: .uk-navbar-container; cls-active: uk-navbar-sticky; cls-inactive: uk-navbar-transparent uk-light; end: ! *; offset: 80\">\n\n        <nav class=\"uk-navbar-container uk-light\">\n            <div class=\"uk-container uk-container-expand\">\n                <div uk-navbar>\n\n                    <ul class=\"uk-navbar-nav\">\n                        <li class=\"uk-active\"><a href=\"#\">Active</a></li>\n                        <li>\n                            <a href=\"#\">Parent</a>\n                            <div class=\"uk-navbar-dropdown\">\n                                <ul class=\"uk-nav uk-navbar-dropdown-nav\">\n                                    <li class=\"uk-active\"><a href=\"#\">Active</a></li>\n                                    <li><a href=\"#\">Item</a></li>\n                                    <li><a href=\"#\">Item</a></li>\n                                </ul>\n                            </div>\n                        </li>\n                        <li><a href=\"#\">Item</a></li>\n                    </ul>\n\n                </div>\n            </div>\n        </nav>\n    </div>\n\n    <div class=\"uk-section uk-light\">\n        <div class=\"uk-container\">\n\n            <p>Lorem ipsum dolor sit amet, consectetur adipiscing elit, sed do eiusmod tempor incididunt ut labore et dolore magna aliqua. Ut enim ad minim veniam, quis nostrud exercitation ullamco laboris nisi ut aliquip ex ea commodo consequat. Duis aute irure dolor in reprehenderit in voluptate velit esse cillum.</p>\n\n            <p>Excepteur sint occaecat cupidatat non proident, sunt in culpa qui officia deserunt mollit anim id est laborum. Lorem ipsum dolor sit amet, consectetur adipiscing elit, sed do eiusmod tempor incididunt ut labore et dolore magna aliqua. Ut enim ad minim veniam, quis nostrud exercitation ullamco laboris.</p>\n\n            <p>Lorem ipsum dolor sit amet, consectetur adipiscing elit, sed do eiusmod tempor incididunt ut labore et dolore magna aliqua. Ut enim ad minim veniam, quis nostrud exercitation ullamco laboris nisi ut aliquip ex ea commodo consequat. Duis aute irure dolor in reprehenderit in voluptate velit esse cillum.</p>\n\n        </div>\n    </div>\n\n</div>"
    },
    {
        "index": 20,
        "heading": "Dropbar transparent mode",
        "html": "<div class=\"uk-section-secondary uk-background-cover uk-preserve-color uk-inverse-light\" style=\"background-image: url('images/dark.jpg');\">\n\n    <div uk-sticky=\"start: 170; animation: uk-animation-slide-top; sel-target: .uk-navbar-container; cls-active: uk-navbar-sticky; cls-inactive: uk-navbar-transparent; end: ! *; offset: 80\">\n\n        <nav class=\"uk-navbar-container\" uk-inverse=\"sel-active: .uk-navbar-transparent\">\n            <div class=\"uk-container\">\n                <div uk-navbar=\"dropbar: true; dropbar-transparent-mode: remove; dropbar-anchor: !.uk-navbar-container; target-y: !.uk-navbar-container\">\n\n                    <div class=\"uk-navbar-left\">\n\n                        <ul class=\"uk-navbar-nav\">\n                            <li class=\"uk-active\"><a href=\"#\">Active</a></li>\n                            <li>\n                                <a href=\"#\">Parent</a>\n                                <div class=\"uk-navbar-dropdown\">\n                                    <ul class=\"uk-nav uk-navbar-dropdown-nav\">\n                                        <li class=\"uk-active\"><a href=\"#\">Active</a></li>\n                                        <li><a href=\"#\">Item</a></li>\n                                        <li class=\"uk-nav-header\">Header</li>\n                                        <li><a href=\"#\">Item</a></li>\n                                        <li><a href=\"#\">Item</a></li>\n                                        <li class=\"uk-nav-divider\"></li>\n                                        <li><a href=\"#\">Item</a></li>\n                                    </ul>\n                                </div>\n                            </li>\n                            <li>\n                                <a href=\"#\">Parent</a>\n                                <div class=\"uk-navbar-dropdown uk-navbar-dropdown-width-2\">\n                                    <div class=\"uk-drop-grid uk-child-width-1-2\" uk-grid>\n                                        <div>\n                                            <ul class=\"uk-nav uk-navbar-dropdown-nav\">\n                                                <li class=\"uk-active\"><a href=\"#\">Active</a></li>\n                                                <li><a href=\"#\">Item</a></li>\n                                                <li class=\"uk-nav-header\">Header</li>\n                                                <li><a href=\"#\">Item</a></li>\n                                                <li><a href=\"#\">Item</a></li>\n                                                <li class=\"uk-nav-divider\"></li>\n                                                <li><a href=\"#\">Item</a></li>\n                                            </ul>\n                                        </div>\n                                        <div>\n                                            <ul class=\"uk-nav uk-navbar-dropdown-nav\">\n                                                <li class=\"uk-active\"><a href=\"#\">Active</a></li>\n                                                <li><a href=\"#\">Item</a></li>\n                                                <li class=\"uk-nav-header\">Header</li>\n                                                <li><a href=\"#\">Item</a></li>\n                                                <li><a href=\"#\">Item</a></li>\n                                                <li class=\"uk-nav-divider\"></li>\n                                                <li><a href=\"#\">Item</a></li>\n                                            </ul>\n                                        </div>\n                                    </div>\n                                </div>\n                            </li>\n                        </ul>\n\n                    </div>\n\n                </div>\n            </div>\n        </nav>\n\n    </div>\n\n    <div class=\"uk-section uk-light\">\n        <div class=\"uk-container\">\n\n            <p>Lorem ipsum dolor sit amet, consectetur adipiscing elit, sed do eiusmod tempor incididunt ut labore et dolore magna aliqua. Ut enim ad minim veniam, quis nostrud exercitation ullamco laboris nisi ut aliquip ex ea commodo consequat. Duis aute irure dolor in reprehenderit in voluptate velit esse cillum.</p>\n\n            <p>Excepteur sint occaecat cupidatat non proident, sunt in culpa qui officia deserunt mollit anim id est laborum. Lorem ipsum dolor sit amet, consectetur adipiscing elit, sed do eiusmod tempor incididunt ut labore et dolore magna aliqua. Ut enim ad minim veniam, quis nostrud exercitation ullamco laboris.</p>\n\n            <p>Lorem ipsum dolor sit amet, consectetur adipiscing elit, sed do eiusmod tempor incididunt ut labore et dolore magna aliqua. Ut enim ad minim veniam, quis nostrud exercitation ullamco laboris nisi ut aliquip ex ea commodo consequat. Duis aute irure dolor in reprehenderit in voluptate velit esse cillum.</p>\n\n        </div>\n    </div>\n\n</div>"
    },
    {
        "index": 21,
        "heading": "",
        "html": "<div class=\"uk-section-secondary uk-background-cover uk-preserve-color uk-inverse-light\" style=\"background-image: url('images/dark.jpg');\">\n\n    <div uk-sticky=\"sel-target: .uk-navbar-container; cls-active: uk-navbar-sticky; end: ! *; offset: 80\">\n\n        <nav class=\"uk-navbar-container uk-navbar-transparent uk-position-relative uk-position-z-index-high\" uk-inverse=\"sel-active: .uk-navbar-transparent\">\n            <div class=\"uk-container\">\n                <div uk-navbar=\"dropbar: true; dropbar-transparent-mode: behind; dropbar-anchor: !.uk-navbar-container; target-y: !.uk-navbar-container\">\n\n                    <div class=\"uk-navbar-left\">\n\n                        <ul class=\"uk-navbar-nav\">\n                            <li class=\"uk-active\"><a href=\"#\">Active</a></li>\n                            <li>\n                                <a href=\"#\">Parent</a>\n                                <div class=\"uk-navbar-dropdown\">\n                                    <ul class=\"uk-nav uk-navbar-dropdown-nav\">\n                                        <li class=\"uk-active\"><a href=\"#\">Active</a></li>\n                                        <li><a href=\"#\">Item</a></li>\n                                        <li class=\"uk-nav-header\">Header</li>\n                                        <li><a href=\"#\">Item</a></li>\n                                        <li><a href=\"#\">Item</a></li>\n                                        <li class=\"uk-nav-divider\"></li>\n                                        <li><a href=\"#\">Item</a></li>\n                                    </ul>\n                                </div>\n                            </li>\n                            <li>\n                                <a href=\"#\">Parent</a>\n                                <div class=\"uk-navbar-dropdown uk-navbar-dropdown-width-2\">\n                                    <div class=\"uk-drop-grid uk-child-width-1-2\" uk-grid>\n                                        <div>\n                                            <ul class=\"uk-nav uk-navbar-dropdown-nav\">\n                                                <li class=\"uk-active\"><a href=\"#\">Active</a></li>\n                                                <li><a href=\"#\">Item</a></li>\n                                                <li class=\"uk-nav-header\">Header</li>\n                                                <li><a href=\"#\">Item</a></li>\n                                                <li><a href=\"#\">Item</a></li>\n                                                <li class=\"uk-nav-divider\"></li>\n                                                <li><a href=\"#\">Item</a></li>\n                                            </ul>\n                                        </div>\n                                        <div>\n                                            <ul class=\"uk-nav uk-navbar-dropdown-nav\">\n                                                <li class=\"uk-active\"><a href=\"#\">Active</a></li>\n                                                <li><a href=\"#\">Item</a></li>\n                                                <li class=\"uk-nav-header\">Header</li>\n                                                <li><a href=\"#\">Item</a></li>\n                                                <li><a href=\"#\">Item</a></li>\n                                                <li class=\"uk-nav-divider\"></li>\n                                                <li><a href=\"#\">Item</a></li>\n                                            </ul>\n                                        </div>\n                                    </div>\n                                </div>\n                            </li>\n                        </ul>\n\n                    </div>\n\n                </div>\n            </div>\n        </nav>\n\n    </div>\n\n    <div class=\"uk-section uk-light\">\n        <div class=\"uk-container\">\n\n            <p>Lorem ipsum dolor sit amet, consectetur adipiscing elit, sed do eiusmod tempor incididunt ut labore et dolore magna aliqua. Ut enim ad minim veniam, quis nostrud exercitation ullamco laboris nisi ut aliquip ex ea commodo consequat. Duis aute irure dolor in reprehenderit in voluptate velit esse cillum.</p>\n\n            <p>Excepteur sint occaecat cupidatat non proident, sunt in culpa qui officia deserunt mollit anim id est laborum. Lorem ipsum dolor sit amet, consectetur adipiscing elit, sed do eiusmod tempor incididunt ut labore et dolore magna aliqua. Ut enim ad minim veniam, quis nostrud exercitation ullamco laboris.</p>\n\n            <p>Lorem ipsum dolor sit amet, consectetur adipiscing elit, sed do eiusmod tempor incididunt ut labore et dolore magna aliqua. Ut enim ad minim veniam, quis nostrud exercitation ullamco laboris nisi ut aliquip ex ea commodo consequat. Duis aute irure dolor in reprehenderit in voluptate velit esse cillum.</p>\n\n        </div>\n    </div>\n\n</div>"
    },
    {
        "index": 22,
        "heading": "",
        "html": "<div class=\"uk-section-default uk-background-cover uk-preserve-color\" style=\"background-image: url('images/light.jpg');\">\n\n    <div id=\"test\">\n\n        <div class=\"uk-blend-difference uk-position-z-index-high\" uk-sticky=\"sel-target: .uk-navbar-container; cls-active: uk-navbar-sticky; end: !.uk-section-default; offset: 80\">\n\n            <nav class=\"uk-navbar-container uk-navbar-transparent uk-light\">\n                <div class=\"uk-container\">\n                    <div uk-navbar=\"container: #test; dropbar: true; dropbar-transparent-mode: behind; close-on-scroll: true; dropbar-anchor: !.uk-blend-difference; target-y: #test .uk-navbar-container\">\n\n                        <div class=\"uk-navbar-left\">\n\n                            <ul class=\"uk-navbar-nav\">\n                                <li class=\"uk-active\"><a href=\"#\">Active</a></li>\n                                <li>\n                                    <a href=\"#\">Parent</a>\n                                    <div class=\"uk-navbar-dropdown\">\n                                        <ul class=\"uk-nav uk-navbar-dropdown-nav\">\n                                            <li class=\"uk-active\"><a href=\"#\">Active</a></li>\n                                            <li><a href=\"#\">Item</a></li>\n                                            <li class=\"uk-nav-header\">Header</li>\n                                            <li><a href=\"#\">Item</a></li>\n                                            <li><a href=\"#\">Item</a></li>\n                                            <li class=\"uk-nav-divider\"></li>\n                                            <li><a href=\"#\">Item</a></li>\n                                        </ul>\n                                    </div>\n                                </li>\n                                <li>\n                                    <a href=\"#\">Parent</a>\n                                    <div class=\"uk-navbar-dropdown uk-navbar-dropdown-width-2\">\n                                        <div class=\"uk-drop-grid uk-child-width-1-2\" uk-grid>\n                                            <div>\n                                                <ul class=\"uk-nav uk-navbar-dropdown-nav\">\n                                                    <li class=\"uk-active\"><a href=\"#\">Active</a></li>\n                                                    <li><a href=\"#\">Item</a></li>\n                                                    <li class=\"uk-nav-header\">Header</li>\n                                                    <li><a href=\"#\">Item</a></li>\n                                                    <li><a href=\"#\">Item</a></li>\n                                                    <li class=\"uk-nav-divider\"></li>\n                                                    <li><a href=\"#\">Item</a></li>\n                                                </ul>\n                                            </div>\n                                            <div>\n                                                <ul class=\"uk-nav uk-navbar-dropdown-nav\">\n                                                    <li class=\"uk-active\"><a href=\"#\">Active</a></li>\n                                                    <li><a href=\"#\">Item</a></li>\n                                                    <li class=\"uk-nav-header\">Header</li>\n                                                    <li><a href=\"#\">Item</a></li>\n                                                    <li><a href=\"#\">Item</a></li>\n                                                    <li class=\"uk-nav-divider\"></li>\n                                                    <li><a href=\"#\">Item</a></li>\n                                                </ul>\n                                            </div>\n                                        </div>\n                                    </div>\n                                </li>\n                            </ul>\n\n                        </div>\n\n                    </div>\n                </div>\n            </nav>\n\n        </div>\n\n    </div>\n\n    <div class=\"uk-section\">\n        <div class=\"uk-container\">\n\n            <p>Lorem ipsum dolor sit amet, consectetur adipiscing elit, sed do eiusmod tempor incididunt ut labore et dolore magna aliqua. Ut enim ad minim veniam, quis nostrud exercitation ullamco laboris nisi ut aliquip ex ea commodo consequat. Duis aute irure dolor in reprehenderit in voluptate velit esse cillum.</p>\n\n            <p>Excepteur sint occaecat cupidatat non proident, sunt in culpa qui officia deserunt mollit anim id est laborum. Lorem ipsum dolor sit amet, consectetur adipiscing elit, sed do eiusmod tempor incididunt ut labore et dolore magna aliqua. Ut enim ad minim veniam, quis nostrud exercitation ullamco laboris.</p>\n\n            <p>Lorem ipsum dolor sit amet, consectetur adipiscing elit, sed do eiusmod tempor incididunt ut labore et dolore magna aliqua. Ut enim ad minim veniam, quis nostrud exercitation ullamco laboris nisi ut aliquip ex ea commodo consequat. Duis aute irure dolor in reprehenderit in voluptate velit esse cillum.</p>\n\n        </div>\n    </div>\n\n</div>"
    },
    {
        "index": 23,
        "heading": "Color navbar parts separately",
        "html": "<div class=\"uk-position-relative\">\n\n    <div class=\"uk-position-top\">\n\n        <div uk-sticky=\"sel-target: .uk-navbar-container; cls-active: uk-navbar-sticky; end: !.uk-position-relative; offset: 80\">\n            <nav class=\"uk-navbar-container uk-navbar-transparent\" uk-inverse=\"target: .uk-navbar-left, .uk-navbar-center, .uk-navbar-right\">\n                <div class=\"uk-container\">\n                    <div uk-navbar>\n                        <div class=\"uk-navbar-left\">\n\n                            <ul class=\"uk-navbar-nav\">\n                                <li class=\"uk-active\"><a href=\"#\">Active</a></li>\n                                <li><a href=\"#\">Item</a></li>\n                            </ul>\n\n                        </div>\n                        <div class=\"uk-navbar-center\">\n\n                            <ul class=\"uk-navbar-nav\">\n                                <li class=\"uk-active\"><a href=\"\">Active</a></li>\n                                <li><a href=\"#\">Item</a></li>\n                            </ul>\n\n                        </div>\n                        <div class=\"uk-navbar-right\">\n\n                            <ul class=\"uk-navbar-nav\">\n                                <li class=\"uk-active\"><a href=\"\">Active</a></li>\n                                <li><a href=\"#\">Item</a></li>\n                            </ul>\n\n                        </div>\n                    </div>\n                </div>\n            </nav>\n        </div>\n    </div>\n\n    <div class=\"uk-child-width-1-3@s uk-grid-collapse uk-grid-match\" uk-grid>\n        <div>\n\n            <div class=\"uk-tile uk-tile-default\">\n                <div uk-height-placeholder=\"!.uk-position-relative .uk-position-top\" class=\"uk-margin-remove-adjacent\"></div>\n                <p>Lorem ipsum dolor sit amet, consectetur adipiscing elit.</p>\n            </div>\n\n        </div>\n        <div>\n\n            <div class=\"uk-tile uk-tile-primary\">\n                <div uk-height-placeholder=\"!.uk-position-relative .uk-position-top\" class=\"uk-margin-remove-adjacent\"></div>\n                <p>Lorem ipsum dolor sit amet, consectetur adipiscing elit.</p>\n            </div>\n\n        </div>\n        <div>\n\n            <div class=\"uk-tile uk-tile-secondary\">\n                <div uk-height-placeholder=\"!.uk-position-relative .uk-position-top\" class=\"uk-margin-remove-adjacent\"></div>\n                <p>Lorem ipsum dolor sit amet, consectetur adipiscing elit.</p>\n            </div>\n\n        </div>\n    </div>\n\n    <div class=\"uk-child-width-1-3@s uk-grid-collapse uk-grid-match\" uk-grid>\n        <div>\n\n            <div class=\"uk-tile uk-tile-primary\">\n                <p>Lorem ipsum dolor sit amet, consectetur adipiscing elit.</p>\n            </div>\n\n        </div>\n        <div>\n\n            <div class=\"uk-tile uk-tile-muted\">\n                <p>Lorem ipsum dolor sit amet, consectetur adipiscing elit.</p>\n            </div>\n\n        </div>\n        <div>\n\n            <div class=\"uk-tile uk-tile-default\">\n                <p>Lorem ipsum dolor sit amet, consectetur adipiscing elit.</p>\n            </div>\n\n        </div>\n    </div>\n\n    <div class=\"uk-child-width-1-3@s uk-grid-collapse uk-grid-match\" uk-grid>\n        <div>\n\n            <div class=\"uk-tile uk-tile-default\">\n                <p>Lorem ipsum dolor sit amet, consectetur adipiscing elit.</p>\n            </div>\n\n        </div>\n        <div>\n\n            <div class=\"uk-tile uk-tile-secondary\">\n                <p>Lorem ipsum dolor sit amet, consectetur adipiscing elit.</p>\n            </div>\n\n        </div>\n        <div>\n\n            <div class=\"uk-tile uk-tile-muted\">\n                <p>Lorem ipsum dolor sit amet, consectetur adipiscing elit.</p>\n            </div>\n\n        </div>\n    </div>\n\n</div>"
    }
]